vsave/__init__.py
vsave-0.3.dist-info/METADATA
vsave-0.3.dist-info/WHEEL
vsave-0.3.dist-info/top_level.txt
vsave-0.3.dist-info/RECORD
