Metadata-Version: 2.1
Name: vsave
Version: 0.3
Summary: Save the variable.
Home-page: https://github.com/puter1234
Author: puter
Author-email: john.minjun.kim@gmail.com
License: MIT
Platform: UNKNOWN
Classifier: License :: OSI Approved :: MIT License
